<?xml version="1.0" encoding="utf-8"?>
<items><story><date>07:10 02 January 2007 (UTC)</date><text>NEW YORK Jan 2 The Chicago Board of Trade
BOT.N said on Tuesday its volume for December rose 33 percent
from a year ago to 55,344,340 contracts. Average daily volume rose 40 percent from the same month a
year ago to 2,767,217 contracts.


</text><link>http://www.reuters.com/article/2007/01/02/cbot-volume-idUSWEN166220070102</link><sectors></sectors><title>cbot december monthly volume rises 33 pct</title></story></items>