<?xml version="1.0" encoding="utf-8"?>
<items><story><date>02:43 02 January 2007 (UTC)</date><text>AMSTERDAM Jan 2 Dutch telecoms group KPN
(KPN.AS)KPN.N said on Tuesday it will restructure its
organisation to improve market share, turnover and profitability
by serving clients based on a business and consumer approach. KPN's fixed line and mobile divisions will merge in new
groups called business market and consumers market to focus on
clients instead of technology and products, KPN said in a
statement.

</text><link>http://www.reuters.com/article/2007/01/02/kpn-reorganisation-idUSWEA141220070102</link><sectors></sectors><title>kpn reorganises divisions to focus on clients</title></story></items>