<?xml version="1.0" encoding="utf-8"?>
<items><story><date>05:35 03 January 2007 (UTC)</date><text>AMSTERDAM Jan 3 Dutch bank ABN AMRO NV
AAH.ASABN.N said on Wednesday its Antonveneta unit had sold
part of its non-performing loan portfolio to GE Commercial
Finance Services Italy and Pirelli RE. ABN AMRO, the Netherlands biggest bank, said the portfolio
consisted of mixed commercial loans with a gross book value of
about 1 billion euros ($1.3 billion), secured by Italian real
estate assets.
"An exclusive mandate has been signed with GE and Pirelli
for an additional portion of non-performing loans, of which
approximately 3 billion euros refers to NPLs (non-performing
loans) and approximately 2 billion euros refers to a securitized
NPL portfolio," ABN AMRO said.



</text><link>http://www.reuters.com/article/2007/01/03/abnamro-antonveneta-idUSWEA142520070103</link><sectors></sectors><title>abn amro unit sells some non - performing loans</title></story></items>