<?xml version="1.0" encoding="utf-8"?>
<items><story><date>17:18 03 January 2007 (UTC)</date><text>Jan 3 Carrier Access Corp. CACS.O, the
communications equipment maker, said it expects to report a
fourth-quarter loss, mainly due to lower-than-expected orders
from wireless customers. Loss for the quarter is expected to be 24 cents to 28 cents
a share, including option expense, on revenue of $12.3 million
to $12.5 million. Excluding items, Carrier Access expects to
post a loss of 21 cents to 25 cents a share.
 (Reporting by Rakesh Dubey in Bangalore)


</text><link>http://www.reuters.com/article/2007/01/03/carrieraccess-outlook-idUSWNAS663620070103</link><sectors><value><value>Markets</value></value></sectors><title>carrier access sees q4 loss on lower orders</title></story></items>